setup.py
docker_registry/__init__.py
docker_registry/../config/config_fds.yml
docker_registry/drivers/__init__.py
docker_registry/drivers/fds.py
docker_registry/drivers/test.py
docker_registry_driver_fds.egg-info/PKG-INFO
docker_registry_driver_fds.egg-info/SOURCES.txt
docker_registry_driver_fds.egg-info/dependency_links.txt
docker_registry_driver_fds.egg-info/namespace_packages.txt
docker_registry_driver_fds.egg-info/requires.txt
docker_registry_driver_fds.egg-info/top_level.txt
docker_registry_driver_fds.egg-info/zip-safe