Metadata-Version: 1.1
Name: docker-registry-driver-fds
Version: 1.0.6
Summary: Docker registry driver fds
Home-page: UNKNOWN
Author: tobe
Author-email: tobeg3oogle@gmail.com
License: UNKNOWN
Platform: Independent
Classifier: Development Status :: 4 - Beta
Classifier: Intended Audience :: Developers
Classifier: Programming Language :: Python
Classifier: Programming Language :: Python :: 2.6
Classifier: Programming Language :: Python :: 2.7
Classifier: Programming Language :: Python :: 3.4
Classifier: Programming Language :: Python :: Implementation :: CPython
Classifier: Operating System :: OS Independent
Classifier: Topic :: Utilities
Classifier: License :: OSI Approved :: Apache Software License
